<?xml version="1.0" encoding="utf-8" ?><dwsync><file name="carouseltabs.js" server="training.dequecloud.com/training.dequecloud.com/htdocs/" local="3504124597" remote="319783739147989685" Dst="-1" /><file name="index.html" server="training.dequecloud.com/training.dequecloud.com/htdocs/" local="3500648022" remote="319783739144513110" Dst="-1" /><file name="tabs.js" server="training.dequecloud.com/training.dequecloud.com/htdocs/" local="3500634346" remote="319783739144499438" Dst="-1" /><file name="tabcarousel.css" server="training.dequecloud.com/training.dequecloud.com/htdocs/" local="3504124059" remote="319783739147989148" Dst="-1" /><file name="astronauts-large.png" server="training.dequecloud.com/training.dequecloud.com/htdocs/" local="3504117322" remote="319783739147982456" Dst="-1" /><file name="astronauts150.png" server="training.dequecloud.com/training.dequecloud.com/htdocs/" local="3504117354" remote="319783739147982456" Dst="-1" /><file name="safety.png" server="training.dequecloud.com/training.dequecloud.com/htdocs/" local="3504117590" remote="319783739147982797" Dst="-1" /><file name="sale.png" server="training.dequecloud.com/training.dequecloud.com/htdocs/" local="3504117689" remote="319783739147982797" Dst="-1" /></dwsync>